dgmaxclient/__init__.py
dgmaxclient/authentication.py
dgmaxclient/client.py
dgmaxclient/endpoints.py
dgmaxclient/error_handlers.py
dgmaxclient/exceptions.py
dgmaxclient/py.typed
dgmaxclient/request_strategies.py
dgmaxclient/retrying.py
dgmaxclient/models/__init__.py
dgmaxclient/models/base.py
dgmaxclient/models/certification.py
dgmaxclient/models/companies.py
dgmaxclient/models/documents.py
dgmaxclient/models/pagination.py
dgmaxclient/resources/__init__.py
dgmaxclient/resources/base.py
dgmaxclient/resources/certification.py
dgmaxclient/resources/companies.py
dgmaxclient/resources/credit_notes.py
dgmaxclient/resources/debit_notes.py
dgmaxclient/resources/exports.py
dgmaxclient/resources/fiscal_invoices.py
dgmaxclient/resources/governmental.py
dgmaxclient/resources/invoices.py
dgmaxclient/resources/minor_expenses.py
dgmaxclient/resources/payments_abroad.py
dgmaxclient/resources/purchases.py
dgmaxclient/resources/received_documents.py
dgmaxclient/resources/special_regimes.py
dgmaxclient-1.2.0.dist-info/METADATA
dgmaxclient-1.2.0.dist-info/WHEEL
dgmaxclient-1.2.0.dist-info/RECORD
