Metadata-Version: 2.4
Name: dgmaxclient
Version: 1.2.0
Summary: Python SDK for DGMax API - Electronic fiscal document processing for Dominican Republic
Project-URL: Homepage, https://dgmax.do
Project-URL: Documentation, https://docs.dgmax.do
Author-email: DGMax <support@dgmax.do>
License-Expression: MIT
Classifier: Development Status :: 4 - Beta
Classifier: Intended Audience :: Developers
Classifier: License :: OSI Approved :: MIT License
Classifier: Programming Language :: Python :: 3
Classifier: Programming Language :: Python :: 3.8
Classifier: Programming Language :: Python :: 3.9
Classifier: Programming Language :: Python :: 3.10
Classifier: Programming Language :: Python :: 3.11
Classifier: Programming Language :: Python :: 3.12
Classifier: Topic :: Software Development :: Libraries :: Python Modules
Classifier: Typing :: Typed
Requires-Python: >=3.8
Requires-Dist: api-client>=1.3.1
Requires-Dist: email-validator>=2.0
Requires-Dist: eval-type-backport>=0.2.0; python_version < '3.10'
Requires-Dist: pydantic>=2.0
Requires-Dist: requests>=2.28.0
Requires-Dist: tenacity>=8.0
Provides-Extra: dev
Requires-Dist: httpx>=0.24.0; extra == 'dev'
Requires-Dist: mypy>=1.0; extra == 'dev'
Requires-Dist: pytest-cov>=4.0; extra == 'dev'
Requires-Dist: pytest>=7.0; extra == 'dev'
Requires-Dist: respx>=0.20; extra == 'dev'
Requires-Dist: ruff>=0.1; extra == 'dev'
